ilanguage/__init__.py
ilanguage/__main__.py
ilanguage/Main/__init__.py
ilanguage/Main/_ast.py
ilanguage/Main/_errors.py
ilanguage/Main/_types.py
ilanguage/Main/lexer.py
ilanguage/Main/parser.py
ilanguage/Main/shell.py
ilanguage/Modules/_core/Console.py
ilanguage/Modules/_core/Math.py
ilanguage/Modules/_core/Random.py
ilanguage/Modules/_core/__init__.py
ilanguage/Tests/test_console.py
ilanguage/Tests/test_lexer.py
ilanguage/Tests/test_math.py
I_Language-0.0.9.dist-info/LICENSE
I_Language-0.0.9.dist-info/METADATA
I_Language-0.0.9.dist-info/WHEEL
I_Language-0.0.9.dist-info/top_level.txt
I_Language-0.0.9.dist-info/RECORD
