Metadata-Version: 2.1
Name: I-Language
Version: 0.0.9
Summary: The I programming language is a high level programming language written in pure python.
Author: MasterOktagon
Author-email: ElBe-Plaq <elbe.dev.plaq@gmail.com>
License: MIT License
Project-URL: Homepage, https://github.com/I-Language-Development/i-language
Project-URL: Bug Tracker, https://github.com/I-Language-Development/i-language/issues
Keywords: i language,programming-language,language
Classifier: Development Status :: 2 - Pre-Alpha
Classifier: Framework :: Pytest
Classifier: Programming Language :: Python
Classifier: Programming Language :: Python :: 3 :: Only
Classifier: Programming Language :: Python :: 3.7
Classifier: Programming Language :: Python :: 3.8
Classifier: Programming Language :: Python :: 3.9
Classifier: Programming Language :: Python :: 3.10
Classifier: Programming Language :: Python :: 3.11
Classifier: Programming Language :: Python :: Implementation :: CPython
Classifier: License :: OSI Approved :: MIT License
Classifier: Operating System :: OS Independent
Requires-Python: >=3.7
License-File: LICENSE
Requires-Dist: typing-extensions (>=4.5.0)
Provides-Extra: dev
Requires-Dist: autopep8 (==2.0.2) ; extra == 'dev'
Requires-Dist: bandit (==1.7.5) ; extra == 'dev'
Requires-Dist: black (==23.3.0) ; extra == 'dev'
Requires-Dist: build (==0.10.0) ; extra == 'dev'
Requires-Dist: pipreqs (==0.4.11) ; extra == 'dev'
Requires-Dist: pylint-runner (==0.6.0) ; extra == 'dev'
Requires-Dist: pylint-secure-coding-standard (==1.4.1) ; extra == 'dev'
Requires-Dist: pytest (==7.2.2) ; extra == 'dev'
Requires-Dist: pytest-cov (==4.0.0) ; extra == 'dev'
Requires-Dist: pytest-picked (==0.4.6) ; extra == 'dev'
Requires-Dist: pytest-pretty (==1.1.1) ; extra == 'dev'
Requires-Dist: ruff (==0.0.260) ; extra == 'dev'
Requires-Dist: twine (==4.0.2) ; extra == 'dev'
Provides-Extra: docs
Requires-Dist: mkdocstrings[python] (==0.20.0) ; extra == 'docs'
Requires-Dist: mkdocs-material (==9.1.4) ; extra == 'docs'
Requires-Dist: mkdocs-section-index (==0.3.5) ; extra == 'docs'
